mathrixpy
