Metadata-Version: 2.1
Name: mathrixpy
Version: 1.4
Summary: mathrixpy es una biblioteca de Python para realizar operaciones matriciales. Permite la creación, manipulación y operaciones aritméticas con matrices. Esta biblioteca es útil para aplicaciones matemáticas y científicas que requieren cálculos matriciales.
Home-page: https://github.com/Ampere-G/mathrixPy
Author: AmJoJADeOrg
Author-email: glroberto1810@gmail.com
License: MIT
Classifier: Programming Language :: Python :: 3
Classifier: License :: OSI Approved :: MIT License
Classifier: Operating System :: OS Independent
Requires-Python: >=3.6
License-File: LICENSE
